splogger/__init__.py
splogger/logger.py
splogger-0.1.4.dist-info/METADATA
splogger-0.1.4.dist-info/RECORD
splogger-0.1.4.dist-info/WHEEL
splogger-0.1.4.dist-info/top_level.txt
