Metadata-Version: 2.1
Name: splogger
Version: 0.1.4
Summary: Simple Python Logger
Home-page: https://github.com/WIN32GG/python-simple-logger
Author: win32gg
Author-email: gregor.jouet@laposte.net
License: MIT
Platform: UNKNOWN
Requires-Python: >=3.4, <4
Requires-Dist: colorama
Requires-Dist: wrapt
